MANIFEST.in
base_calendar_data.xml
base_calendar_view.xml
crm_meeting_data.xml
crm_meeting_demo.xml
crm_meeting_view.xml
setup.py
./__init__.py
./__openerp__.py
./base_calendar.py
./crm_meeting.py
i18n/af.po
i18n/ar.po
i18n/base_calendar.pot
i18n/bg.po
i18n/bn.po
i18n/bs.po
i18n/ca.po
i18n/cs.po
i18n/da.po
i18n/de.po
i18n/el.po
i18n/es.po
i18n/es_CR.po
i18n/es_EC.po
i18n/es_MX.po
i18n/es_PY.po
i18n/es_VE.po
i18n/et.po
i18n/fa.po
i18n/fi.po
i18n/fr.po
i18n/gl.po
i18n/he.po
i18n/hr.po
i18n/hu.po
i18n/id.po
i18n/it.po
i18n/ja.po
i18n/ln.po
i18n/lt.po
i18n/lv.po
i18n/mk.po
i18n/mn.po
i18n/nb.po
i18n/nl.po
i18n/pl.po
i18n/pt.po
i18n/pt_BR.po
i18n/ro.po
i18n/ru.po
i18n/sk.po
i18n/sl.po
i18n/sq.po
i18n/sr.po
i18n/sr@latin.po
i18n/sv.po
i18n/th.po
i18n/tr.po
i18n/vi.po
i18n/zh_CN.po
i18n/zh_TW.po
images/base_calendar1.jpeg
images/base_calendar2.jpeg
images/base_calendar3.jpeg
images/base_calendar4.jpeg
openerp_base_calendar.egg-info/PKG-INFO
openerp_base_calendar.egg-info/SOURCES.txt
openerp_base_calendar.egg-info/dependency_links.txt
openerp_base_calendar.egg-info/requires.txt
openerp_base_calendar.egg-info/top_level.txt
security/calendar_security.xml
security/ir.model.access.csv
static/src/img/icon.png
test/base_calendar_test.yml
test/test_crm_recurrent_meeting_case2.yml